tsplot/__init__.py
tsplot/data.py
tsplot/plot.py
tsplot/time.py
tsplot/version.py
tsplot-0.0.2.dist-info/LICENCE
tsplot-0.0.2.dist-info/METADATA
tsplot-0.0.2.dist-info/WHEEL
tsplot-0.0.2.dist-info/top_level.txt
tsplot-0.0.2.dist-info/RECORD
