Metadata-Version: 2.1
Name: tsplot
Version: 0.0.2
Summary: tsplot is a Python package, built on matplotlib, for plotting time series data 
Home-page: http://github.com/brett-hosking/tsplot
Author: brett hosking
Author-email: wilski@noc.ac.uk
License: MIT
Platform: UNKNOWN
Requires-Dist: matplotlib (>=2.2.3)
Requires-Dist: numpy (>=1.16.4)
Requires-Dist: pandas (>=0.23.4)
